CHANGELOG.md
LICENSE
MANIFEST.in
NOTICE
README.md
setup.cfg
setup.py
encrypticoin_etalon/__init__.py
encrypticoin_etalon.egg-info/PKG-INFO
encrypticoin_etalon.egg-info/SOURCES.txt
encrypticoin_etalon.egg-info/dependency_links.txt
encrypticoin_etalon.egg-info/requires.txt
encrypticoin_etalon.egg-info/top_level.txt
encrypticoin_etalon/contract/BEP20EtalonToken.sol
encrypticoin_etalon/contract/BEP20EtalonToken.sol.abi
encrypticoin_etalon/contract/BEP20EtalonToken.sol.bin
encrypticoin_etalon/contract/BEP20EtalonToken.sol.scv
encrypticoin_etalon/contract/BEP20EtalonToken.sol.sha256
encrypticoin_etalon/contract/IBEP20.sol
encrypticoin_etalon/contract/README.txt
encrypticoin_etalon/contract/__init__.py
encrypticoin_etalon/contract/openzeppelin-contracts-4.7.3-Context.sol
encrypticoin_etalon/contract/openzeppelin-contracts-4.7.3-ERC20.sol
encrypticoin_etalon/contract/openzeppelin-contracts-4.7.3-IERC20.sol
encrypticoin_etalon/contract/openzeppelin-contracts-4.7.3-IERC20Metadata.sol
encrypticoin_etalon/contract/openzeppelin-contracts-4.7.3-Ownable.sol
encrypticoin_etalon/utility/__init__.py
encrypticoin_etalon/utility/compile.py
requirements/base.in