Metadata-Version: 2.1
Name: encrypticoin-etalon
Version: 1.0.0
Summary: Etalon token implementation by Encrypticoin UAB
Home-page: https://github.com/encrypticoin-uab/encrypticoin-etalon
Author: Nándor Mátravölgyi
Author-email: dev@etalon.cash
License: Apache 2.0
Classifier: Programming Language :: Python :: 3
Classifier: Intended Audience :: Developers
Classifier: License :: OSI Approved :: Apache Software License
Requires-Python: >=3.8
License-File: LICENSE
License-File: NOTICE
